{
  "schema_version": 1,
  "mode": "historical",
  "failure_mode": "spending_shortfall",
  "run_count": 16,
  "display_path_kind": "median",
  "start_year": 2026,
  "end_year": 2066,
  "retirement_year": 2034,
  "success_settings": {
    "failure_mode": "spending_shortfall",
    "minimum_spending_funded_ratio": 1.0,
    "allow_home_equity_for_spending": false,
    "allow_debt_for_spending": false,
    "failure_grace_period_months": 6.0,
    "custom_failure_column": null,
    "custom_failure_operator": "<",
    "custom_failure_threshold": 0.0
  },
  "terminal_total_net_worth": 20253396.525402583,
  "terminal_investable_net_worth": 18122522.943467446,
  "success_rate": 1.0,
  "failure_rate": 0.0,
  "probability_of_success": 1.0,
  "terminal_total_net_worth_p10": 15838414.331420433,
  "terminal_total_net_worth_p50": 20253396.525402583,
  "terminal_total_net_worth_p90": 24005023.608609922,
  "terminal_investable_net_worth_p10": 13707540.749485292,
  "terminal_investable_net_worth_p50": 18122522.943467446,
  "terminal_investable_net_worth_p90": 21874150.026674785,
  "median_terminal_net_worth": 20253396.525402583,
  "median_terminal_liquid_net_worth": 18122522.943467446,
  "worst_decile_terminal_net_worth": 15838414.331420433,
  "failed_run_count": 0,
  "successful_run_count": 16,
  "first_failure_period_distribution": [],
  "first_failure_year_p10": null,
  "first_failure_year_p50": null,
  "first_failure_year_p90": null,
  "run_labels": [
    "1970-2010",
    "1971-2011",
    "1972-2012",
    "1973-2013",
    "1974-2014",
    "1975-2015",
    "1976-2016",
    "1977-2017",
    "1978-2018",
    "1979-2019",
    "1980-2020",
    "1981-2021",
    "1982-2022",
    "1983-2023",
    "1984-2024",
    "1985-2025"
  ],
  "probability_of_spending_shortfall": 0.0,
  "probability_of_liquid_depletion": 0.0,
  "probability_of_net_worth_below_zero": 0.0,
  "probability_of_home_equity_required": 0.0,
  "peak_current_failure_trigger_rate": 0.0,
  "peak_current_failure_trigger_year": 2026,
  "peak_temporary_pressure_rate": 0.0,
  "peak_temporary_pressure_year": 2026,
  "retirement_success_through_year_rate": 1.0,
  "retirement_current_failure_trigger_rate": 0.0,
  "retirement_temporary_pressure_rate": 0.0,
  "retirement_total_net_worth_p10": 2090631.5816884171,
  "retirement_total_net_worth_p50": 2865444.1160637983,
  "retirement_total_net_worth_p90": 3010403.561118709,
  "data_as_of_clamped": false,
  "clamped_start_year": 2026
}